{
    "players": [
        {
            "id": "1761001616",
            "username": "Franz_von_Gespenst",
            "has_jopka": false,
            "wins": 41,
            "photo_url": "https://t.me/i/userpic/320/Ak-U6i0j5tUDrhC6Y8YHVrn0FBhF6ZkNUDOwJHF1I50.svg"
        },
        {
            "id": "720702086",
            "username": "YaroshNikita",
            "has_jopka": true,
            "wins": 48,
            "photo_url": "https://t.me/i/userpic/320/-nY1NJt3iKXeE7rwapmpZafau0p7SLhVfgUq9Lq_iBA.svg"
        },
        {
            "id": "1989947945",
            "username": "waytmer",
            "has_jopka": false,
            "wins": 5,
            "photo_url": "https://t.me/i/userpic/320/rbVF6tolBHFb35TWh8OuP5DzpQhKBgtnSr9nwYiNv1U.svg"
        }
    ],
    "game_state": {
        "jopka_owner": 720702086
    }
}